MANIFEST.in
README.md
setup.py
browler/__init__.py
browler/browler.py
browler/command_line.py
browler/page.py
browler/qe.js
browler.egg-info/PKG-INFO
browler.egg-info/SOURCES.txt
browler.egg-info/dependency_links.txt
browler.egg-info/not-zip-safe
browler.egg-info/requires.txt
browler.egg-info/top_level.txt
browler/plugins/__init__.py
browler/plugins/base.py