Metadata-Version: 1.0
Name: browler
Version: 0.1.3
Summary: Selenium Based Web Crawler
Home-page: https://github.com/brady-vitrano/browler
Author: brady-vitrano
Author-email: bjvitrano@gmail.com
License: MIT
Platform: any
